k8s_schema_merger/__init__.py
k8s_schema_merger/cli.py
k8s_schema_merger/core.py
k8s_schema_merger-0.1.1.dist-info/entry_points.txt
k8s_schema_merger-0.1.1.dist-info/WHEEL
k8s_schema_merger-0.1.1.dist-info/METADATA
k8s_schema_merger-0.1.1.dist-info/RECORD
