Metadata-Version: 2.3
Name: k8s-schema-merger
Version: 0.1.1
Summary: Merge built-in K8s and CRD schemas for yamlls
Author: Funk66
Requires-Python: >=3.12
Classifier: Programming Language :: Python :: 3
Classifier: License :: OSI Approved :: MIT License
Classifier: Operating System :: OS Independent
Requires-Dist: kubernetes==30.1.0
Project-URL: Bug Tracker, https://github.com/funk66/k8s-schema-merger/issues
Project-URL: Homepage, https://github.com/funk66/k8s-schema-merger
